{
  "symbol": "010140",
  "name": "삼성중공업",
  "timestamp": "2025-10-13T07:01:45.725559",
  "score": 0.2,
  "score_percentage": 0.13986013986013987,
  "grade": "C (위험)",
  "recommendation": "SELL",
  "details": {
    "per_score": 0.1,
    "pbr_score": 0.1,
    "roe_score": 0.0,
    "relative_per": 1393.3333333333333,
    "relative_pbr": 152.0819266261535,
    "sector_percentile": 0.0,
    "sector_adjustment": 1.0,
    "sector_context": {
      "symbol": "010140",
      "sector_name": "운송장비",
      "original_score": 0.2,
      "adjusted_score": 0.06400000000000002,
      "contextualization_applied": true,
      "adjustment_reason": "sector_penalty_40_below_adjusted_0.2",
      "sector_sample_adequate": false,
      "sector_sample_penalty": 0.4,
      "sample_adequacy_reason": "critical_sample_size_0_penalty_0.4",
      "sector_score": 30.0,
      "total_adjustment_factor": 0.32000000000000006
    },
    "raw_component_scores": {
      "per": 0.1,
      "pbr": 0.1,
      "roe": 0.0,
      "total": 0.2
    },
    "piotroski_fscore": 0,
    "piotroski_details": {
      "profit": 0,
      "cfo_positive": 0,
      "roa_increase": 0,
      "accrual_quality": 0,
      "debt_decrease": 0,
      "current_ratio_increase": 0,
      "no_dilution": 0,
      "margin_increase": 0,
      "turnover_increase": 0
    },
    "quality_score": 0,
    "sector_bonus": 0,
    "criteria_met": [],
    "mos_score": 0,
    "mos_points": 0,
    "safety_margin": -72.23124999999999,
    "intrinsic_value": 6220.2,
    "confidence": "LOW",
    "risk_penalty": 0,
    "risk_warnings": [],
    "risk_count": 0,
    "score_percentage": 0.13986013986013987,
    "max_possible_score": 143
  },
  "raw_metrics": {
    "per": 298.6666666666667,
    "pbr": 5.04163853252307,
    "roe": 1.688048615800135,
    "market_cap": 19712000000000.0,
    "current_price": 22400.0
  }
}