{
  "symbol": "012330",
  "name": "현대모비스",
  "timestamp": "2025-10-12T18:10:02.698613",
  "score": 49.540143954156356,
  "score_percentage": 33.473070239294834,
  "grade": "C (위험)",
  "recommendation": "SELL",
  "details": {
    "per_score": 16.14627414903404,
    "pbr_score": 17.059579625554175,
    "roe_score": 8.334290179568143,
    "relative_per": -65.7313707451702,
    "relative_pbr": -70.29789812777088,
    "sector_percentile": 33.33716071827257,
    "sector_adjustment": 1.0,
    "sector_context": {
      "symbol": "012330",
      "sector_name": "운송장비",
      "original_score": 41.540143954156356,
      "adjusted_score": 13.292846065330034,
      "contextualization_applied": true,
      "adjustment_reason": "sector_penalty_40_below_adjusted_33.2",
      "sector_sample_adequate": false,
      "sector_sample_penalty": 0.4,
      "sample_adequacy_reason": "critical_sample_size_0_penalty_0.4",
      "sector_score": 30.0,
      "total_adjustment_factor": 0.32
    },
    "raw_component_scores": {
      "per": 16.14627414903404,
      "pbr": 17.059579625554175,
      "roe": 8.334290179568143,
      "total": 41.540143954156356
    },
    "piotroski_fscore": 0,
    "piotroski_details": {
      "profit": 0,
      "cfo_positive": 0,
      "roa_increase": 0,
      "accrual_quality": 0,
      "debt_decrease": 0,
      "current_ratio_increase": 0,
      "no_dilution": 0,
      "margin_increase": 0,
      "turnover_increase": 0
    },
    "quality_score": 0,
    "sector_bonus": 6,
    "criteria_met": [
      "PER",
      "PBR"
    ],
    "mos_score": 2,
    "mos_points": 2,
    "safety_margin": 143.1767337807606,
    "intrinsic_value": 724666.6666666666,
    "confidence": "LOW",
    "risk_penalty": 0,
    "risk_warnings": [],
    "risk_count": 0,
    "score_percentage": 33.473070239294834,
    "max_possible_score": 148
  },
  "raw_metrics": {
    "per": 6.8537258509659615,
    "pbr": 0.5940420374445826,
    "roe": 8.667432143654514,
    "market_cap": 27354900000000.0,
    "current_price": 298000.0
  }
}